cubicweb_comment/__init__.py
cubicweb_comment/__pkginfo__.py
cubicweb_comment/entities.py
cubicweb_comment/hooks.py
cubicweb_comment/schema.py
cubicweb_comment/views.py
cubicweb_comment/data/cubes.comment.css
cubicweb_comment/data/cubes.comment.js
cubicweb_comment/doc/basic_usage.rst
cubicweb_comment/doc/screenshot_comment_section.png
cubicweb_comment/i18n/en.po
cubicweb_comment/i18n/fr.po
cubicweb_comment/migration/1.2.1_Any.py
cubicweb_comment/migration/postcreate.py
cubicweb_comment-3.1.0.dist-info/METADATA
cubicweb_comment-3.1.0.dist-info/WHEEL
cubicweb_comment-3.1.0.dist-info/entry_points.txt
cubicweb_comment-3.1.0.dist-info/top_level.txt
cubicweb_comment-3.1.0.dist-info/RECORD
